odoo8_addon_account_bank_statement_import_mt940_nl_ing-8.0.0.4.0-py2.7-nspkg.pth
odoo8_addon_account_bank_statement_import_mt940_nl_ing-8.0.0.4.0.dist-info/top_level.txt
odoo8_addon_account_bank_statement_import_mt940_nl_ing-8.0.0.4.0.dist-info/WHEEL
odoo8_addon_account_bank_statement_import_mt940_nl_ing-8.0.0.4.0.dist-info/RECORD
odoo8_addon_account_bank_statement_import_mt940_nl_ing-8.0.0.4.0.dist-info/metadata.json
odoo8_addon_account_bank_statement_import_mt940_nl_ing-8.0.0.4.0.dist-info/DESCRIPTION.rst
odoo8_addon_account_bank_statement_import_mt940_nl_ing-8.0.0.4.0.dist-info/METADATA
odoo8_addon_account_bank_statement_import_mt940_nl_ing-8.0.0.4.0.dist-info/namespace_packages.txt
odoo_addons/account_bank_statement_import_mt940_nl_ing/account_bank_statement_import.py
odoo_addons/account_bank_statement_import_mt940_nl_ing/__openerp__.py
odoo_addons/account_bank_statement_import_mt940_nl_ing/__init__.py
odoo_addons/account_bank_statement_import_mt940_nl_ing/README.rst
odoo_addons/account_bank_statement_import_mt940_nl_ing/mt940.py
odoo_addons/account_bank_statement_import_mt940_nl_ing/i18n/es.po
odoo_addons/account_bank_statement_import_mt940_nl_ing/i18n/lt_LT.po
odoo_addons/account_bank_statement_import_mt940_nl_ing/i18n/sl.po
odoo_addons/account_bank_statement_import_mt940_nl_ing/i18n/nl.po
odoo_addons/account_bank_statement_import_mt940_nl_ing/i18n/de.po
odoo_addons/account_bank_statement_import_mt940_nl_ing/i18n/fr.po
odoo_addons/account_bank_statement_import_mt940_nl_ing/i18n/pt_BR.po
odoo_addons/account_bank_statement_import_mt940_nl_ing/test_files/test-ing-old.940
odoo_addons/account_bank_statement_import_mt940_nl_ing/test_files/test-ing.940
odoo_addons/account_bank_statement_import_mt940_nl_ing/tests/__init__.py
odoo_addons/account_bank_statement_import_mt940_nl_ing/tests/test_import_bank_statement.py
odoo_addons/account_bank_statement_import_mt940_nl_ing/demo/demo_data.xml
